{
    "title": "name of your paper",
    "authors": {
        "author1": "your name"
    },
    "compounds": {
        "c1": {
            "commonName": "water",
            "ID": "c1"
        }
    },
    "pureOrMixtureData": {
        "pom1": {
            "ID": "pom1",
            "comps": [
                "c1"
            ],
            "properties": {
                "pdens": {
                    "propName": "Mass density",
                    "ID": "pdens",
                    "propGroup": "VolumetricProp",
                    "method": "experiment",
                    "unit": "kg/m3"
                }
            },
            "variables": {
                "vtemp": {
                    "varName": "Temperature",
                    "ID": "vtemp",
                    "unit": "K",
                    "varType": "eTemperature"
                }
            },
            "measurements": {
                "meas1": {
                    "ID": "meas1",
                    "properties": {
                        "pdens": {
                            "measurementID": "meas1",
                            "propID": "pdens",
                            "value": 1000
                        }
                    },
                    "variables": {
                        "vtemp": {
                            "measurementID": "meas1",
                            "varID": "vtemp",
                            "value": 293.15
                        }
                    }
                }
            }
        }
    }
}